carp/__init__.py
carp/channel/__init__.py
carp/channel/channel.py
carp/channel/exceptions.py
carp/channel/unix_socket_channel.py
carp/channel/tests/__init__.py
carp/channel/tests/test_unix_channel.py
carp/host/__init__.py
carp/host/host.py
carp/host/tests/__init__.py
carp/host/tests/test_host_announce.py
carp/host/tests/test_host_call.py
carp/host/tests/test_host_connect.py
carp/serializer/__init__.py
carp/serializer/json_serializer.py
carp/serializer/protobuf_serializer.py
carp/serializer/serializable.py
carp/serializer/serializer.py
carp/serializer/protobuf/__init__.py
carp/serializer/protobuf/compiled_python/call_data_pb2.py
carp/serializer/protobuf/compiled_python/envelope_pb2.py
carp/serializer/protobuf/compiled_python/pytypes_pb2.py
carp/serializer/tests/__init__.py
carp/serializer/tests/test_json_serializer.py
carp/serializer/tests/test_protobuf_serializer.py
carp/service/__init__.py
carp/service/api_class.py
carp/service/api_function.py
carp/service/call_data.py
carp/service/service.py
carp/service/tests/test_api_class.py
carp_rpc-0.0.3.dist-info/LICENSE.txt
carp_rpc-0.0.3.dist-info/METADATA
carp_rpc-0.0.3.dist-info/WHEEL
carp_rpc-0.0.3.dist-info/top_level.txt
carp_rpc-0.0.3.dist-info/RECORD
